Workbook

Sheet Inputs
A1: Fixed Income Sensitivity Model
A3: Input | B3: Value
A4: Face Value | B4: 1000
A5: Annual Coupon Rate | B5: 0.08
A6: Years to Maturity | B6: 5
A7: Payments per Year | B7: 2
A8: Annual Yield to Maturity | B8: 0.1
A9: Shock 1 (bps) | B9: 50
A10: Shock 2 (bps) | B10: 100
A11: Shock 3 (bps) | B11: -50
A13: Derived Item | B13: Value
A14: Total Periods | B14: =B6*B7 -> 10
A15: Coupon per Period | B15: =B4*B5/B7 -> 40
A16: Yield per Period | B16: =B8/B7 -> 0.05

Sheet Bond Pricing
A1: Period | B1: Time (Years) | C1: Cupon | D1: Principal | E1: Total Cash Flow | F1: Discount Factor | G1: Present Value | H1: t * PV | I1: t(t+1)*PV | J1: Convexity Term
A2: 1 | B2: =+A2/Inputs!$B$7 -> 0.5 | C2: =+Inputs!$B$15 -> 40 | D2: =+IF(A2=Inputs!$B$14,Inputs!$B$4,0) -> 0 | E2: =+C2+D2 -> 40 | F2: =1/(1+Inputs!$B$16)^A2 -> 0.95238095 | G2: =+E2*F2 -> 38.095238 | H2: =+B2*G2 -> 19.047619 | I2: =+A2*(A2+1)*G2 -> 76.190476 | J2: =A2*(A2+1)*E2/((1+Inputs!$B$16)^(A2+2)) -> 69.107008
A3: =A2+1 -> 2 | B3: =+A3/Inputs!$B$7 -> 1 | C3: =+Inputs!$B$15 -> 40 | D3: =+IF(A3=Inputs!$B$14,Inputs!$B$4,0) -> 0 | E3: =+C3+D3 -> 40 | F3: =1/(1+Inputs!$B$16)^A3 -> 0.90702948 | G3: =+E3*F3 -> 36.281179 | H3: =+B3*G3 -> 36.281179 | I3: =+A3*(A3+1)*G3 -> 217.68707 | J3: =A3*(A3+1)*E3/((1+Inputs!$B$16)^(A3+2)) -> 197.44859
A4: =A3+1 -> 3 | B4: =+A4/Inputs!$B$7 -> 1.5 | C4: =+Inputs!$B$15 -> 40 | D4: =+IF(A4=Inputs!$B$14,Inputs!$B$4,0) -> 0 | E4: =+C4+D4 -> 40 | F4: =1/(1+Inputs!$B$16)^A4 -> 0.8638376 | G4: =+E4*F4 -> 34.553504 | H4: =+B4*G4 -> 51.830256 | I4: =+A4*(A4+1)*G4 -> 414.64205 | J4: =A4*(A4+1)*E4/((1+Inputs!$B$16)^(A4+2)) -> 376.09256
A5: =A4+1 -> 4 | B5: =+A5/Inputs!$B$7 -> 2 | C5: =+Inputs!$B$15 -> 40 | D5: =+IF(A5=Inputs!$B$14,Inputs!$B$4,0) -> 0 | E5: =+C5+D5 -> 40 | F5: =1/(1+Inputs!$B$16)^A5 -> 0.82270247 | G5: =+E5*F5 -> 32.908099 | H5: =+B5*G5 -> 65.816198 | I5: =+A5*(A5+1)*G5 -> 658.16198 | J5: =A5*(A5+1)*E5/((1+Inputs!$B$16)^(A5+2)) -> 596.97232
A6: =A5+1 -> 5 | B6: =+A6/Inputs!$B$7 -> 2.5 | C6: =+Inputs!$B$15 -> 40 | D6: =+IF(A6=Inputs!$B$14,Inputs!$B$4,0) -> 0 | E6: =+C6+D6 -> 40 | F6: =1/(1+Inputs!$B$16)^A6 -> 0.78352617 | G6: =+E6*F6 -> 31.341047 | H6: =+B6*G6 -> 78.352617 | I6: =+A6*(A6+1)*G6 -> 940.2314 | J6: =A6*(A6+1)*E6/((1+Inputs!$B$16)^(A6+2)) -> 852.8176
A7: =A6+1 -> 6 | B7: =+A7/Inputs!$B$7 -> 3 | C7: =+Inputs!$B$15 -> 40 | D7: =+IF(A7=Inputs!$B$14,Inputs!$B$4,0) -> 0 | E7: =+C7+D7 -> 40 | F7: =1/(1+Inputs!$B$16)^A7 -> 0.7462154 | G7: =+E7*F7 -> 29.848616 | H7: =+B7*G7 -> 89.545848 | I7: =+A7*(A7+1)*G7 -> 1253.6419 | J7: =A7*(A7+1)*E7/((1+Inputs!$B$16)^(A7+2)) -> 1137.0901
A8: =A7+1 -> 7 | B8: =+A8/Inputs!$B$7 -> 3.5 | C8: =+Inputs!$B$15 -> 40 | D8: =+IF(A8=Inputs!$B$14,Inputs!$B$4,0) -> 0 | E8: =+C8+D8 -> 40 | F8: =1/(1+Inputs!$B$16)^A8 -> 0.71068133 | G8: =+E8*F8 -> 28.427253 | H8: =+B8*G8 -> 99.495386 | I8: =+A8*(A8+1)*G8 -> 1591.9262 | J8: =A8*(A8+1)*E8/((1+Inputs!$B$16)^(A8+2)) -> 1443.924
A9: =A8+1 -> 8 | B9: =+A9/Inputs!$B$7 -> 4 | C9: =+Inputs!$B$15 -> 40 | D9: =+IF(A9=Inputs!$B$14,Inputs!$B$4,0) -> 0 | E9: =+C9+D9 -> 40 | F9: =1/(1+Inputs!$B$16)^A9 -> 0.67683936 | G9: =+E9*F9 -> 27.073574 | H9: =+B9*G9 -> 108.2943 | I9: =+A9*(A9+1)*G9 -> 1949.2974 | J9: =A9*(A9+1)*E9/((1+Inputs!$B$16)^(A9+2)) -> 1768.0702
A10: =A9+1 -> 9 | B10: =+A10/Inputs!$B$7 -> 4.5 | C10: =+Inputs!$B$15 -> 40 | D10: =+IF(A10=Inputs!$B$14,Inputs!$B$4,0) -> 0 | E10: =+C10+D10 -> 40 | F10: =1/(1+Inputs!$B$16)^A10 -> 0.64460892 | G10: =+E10*F10 -> 25.784357 | H10: =+B10*G10 -> 116.0296 | I10: =+A10*(A10+1)*G10 -> 2320.5921 | J10: =A10*(A10+1)*E10/((1+Inputs!$B$16)^(A10+2)) -> 2104.8454
A11: =A10+1 -> 10 | B11: =+A11/Inputs!$B$7 -> 5 | C11: =+Inputs!$B$15 -> 40 | D11: =+IF(A11=Inputs!$B$14,Inputs!$B$4,0) -> 1000 | E11: =+C11+D11 -> 1040 | F11: =1/(1+Inputs!$B$16)^A11 -> 0.61391325 | G11: =+E11*F11 -> 638.46978 | H11: =+B11*G11 -> 3192.3489 | I11: =+A11*(A11+1)*G11 -> 70231.676 | J11: =A11*(A11+1)*E11/((1+Inputs!$B$16)^(A11+2)) -> 63702.201
F13: Bond Price | G13: =SUM(G2:G11) -> 922.78265
F14: Macaulay Duration | G14: =SUM(H2:H11)/G13 -> 4.1797946
F15: Modified Duration | G15: =G14/(1+Inputs!$B$16) -> 3.9807567
F16: Convexity (per period² basis) | G16: =SUM(J2:J11)/(G13*(Inputs!$B$7^2)) -> 19.573561

Sheet Sensitivity
A1: Bond Sensitivity Summary
A3: Metric | B3: Value
A4: Base Price | B4: ='Bond Pricing'!G13 -> 922.78265
A5: Macauley Duration | B5: ='Bond Pricing'!G14 -> 4.1797946
A6: Modified Duration | B6: ='Bond Pricing'!G15 -> 3.9807567
A7: Convexity | B7: ='Bond Pricing'!G16 -> 19.573561
A10: Scenario | B10: Shock (bps) | C10: Shock (decimal) | D10: New Yield | E10: Approx % Price Change | F10: Approx Price | G10: Exact Price | H10: Approx Error | I10: Duration-Only % Change | J10: Duration-Only Price
A11: +50 bps | B11: =Inputs!B9 -> 50 | C11: =B11/10000 -> 0.005 | D11: =Inputs!$B$8+C11 -> 0.105 | E11: =-$B$6*C11+0.5*$B$7*(C11^2) -> -0.019659114 | F11: =$B$4*(1+E11) -> 904.64156 | G11: {=SUMPRODUCT('Bond Pricing'!$E$2:$E$11,1/(1+(D11/Inputs!$B$7))^('Bond Pricing'!$A$2:$A$11))} -> 904.63949 | H11: =F11-G11 -> 0.0020670832 | I11: =-$B$6*C11 -> -0.019903784 | J11: =$B$4*(1+I11) -> 904.41578
A12: +100 bps | B12: =Inputs!B10 -> 100 | C12: =B12/10000 -> 0.01 | D12: =Inputs!$B$8+C12 -> 0.11 | E12: =-$B$6*C12+0.5*$B$7*(C12^2) -> -0.038828889 | F12: =$B$4*(1+E12) -> 886.95203 | G12: {=SUMPRODUCT('Bond Pricing'!$E$2:$E$11,1/(1+(D12/Inputs!$B$7))^('Bond Pricing'!$A$2:$A$11))} -> 886.93561 | H12: =F12-G12 -> 0.016412635 | I12: =-$B$6*C12 -> -0.039807567 | J12: =$B$4*(1+I12) -> 886.04892
A13: -50 bps | B13: =Inputs!B11 -> -50 | C13: =B13/10000 -> -0.005 | D13: =Inputs!$B$8+C13 -> 0.095 | E13: =-$B$6*C13+0.5*$B$7*(C13^2) -> 0.020148453 | F13: =$B$4*(1+E13) -> 941.37529 | G13: {=SUMPRODUCT('Bond Pricing'!$E$2:$E$11,1/(1+(D13/Inputs!$B$7))^('Bond Pricing'!$A$2:$A$11))} -> 941.37739 | H13: =F13-G13 -> -0.0020987082 | I13: =-$B$6*C13 -> 0.019903784 | J13: =$B$4*(1+I13) -> 941.14952
A18: Yield | B18: Bond Price
A19: 0.06 | B19: {=SUMPRODUCT('Bond Pricing'!$E$2:$E$11,1/((1+(A19/Inputs!$B$7))^('Bond Pricing'!$A$2:$A$11)))} -> 1085.302
A20: 0.07 | B20: {=SUMPRODUCT('Bond Pricing'!$E$2:$E$11,1/((1+(A20/Inputs!$B$7))^('Bond Pricing'!$A$2:$A$11)))} -> 1041.583
A21: 0.08 | B21: {=SUMPRODUCT('Bond Pricing'!$E$2:$E$11,1/((1+(A21/Inputs!$B$7))^('Bond Pricing'!$A$2:$A$11)))} -> 1000
A22: 0.09 | B22: {=SUMPRODUCT('Bond Pricing'!$E$2:$E$11,1/((1+(A22/Inputs!$B$7))^('Bond Pricing'!$A$2:$A$11)))} -> 960.43641
A23: 0.1 | B23: {=SUMPRODUCT('Bond Pricing'!$E$2:$E$11,1/((1+(A23/Inputs!$B$7))^('Bond Pricing'!$A$2:$A$11)))} -> 922.78265
A24: 0.11 | B24: {=SUMPRODUCT('Bond Pricing'!$E$2:$E$11,1/((1+(A24/Inputs!$B$7))^('Bond Pricing'!$A$2:$A$11)))} -> 886.93561
A25: 0.12 | B25: {=SUMPRODUCT('Bond Pricing'!$E$2:$E$11,1/((1+(A25/Inputs!$B$7))^('Bond Pricing'!$A$2:$A$11)))} -> 852.79826
A26: 0.13 | B26: {=SUMPRODUCT('Bond Pricing'!$E$2:$E$11,1/((1+(A26/Inputs!$B$7))^('Bond Pricing'!$A$2:$A$11)))} -> 820.27924
A27: 0.14 | B27: {=SUMPRODUCT('Bond Pricing'!$E$2:$E$11,1/((1+(A27/Inputs!$B$7))^('Bond Pricing'!$A$2:$A$11)))} -> 789.29255
A28: 0.15 | B28: {=SUMPRODUCT('Bond Pricing'!$E$2:$E$11,1/((1+(A28/Inputs!$B$7))^('Bond Pricing'!$A$2:$A$11)))} -> 759.75717
